config/__init__.py
config/asgi.py
config/settings.py
config/urls.py
config/wsgi.py
wdg_kombu_sdk/__init__.py
wdg_kombu_sdk/admin.py
wdg_kombu_sdk/apps.py
wdg_kombu_sdk/connection.py
wdg_kombu_sdk/consumer.py
wdg_kombu_sdk/models.py
wdg_kombu_sdk/publisher.py
wdg_kombu_sdk/signals.py
wdg_kombu_sdk/tests.py
wdg_kombu_sdk/views.py
wdg_kombu_sdk/migrations/__init__.py
wdg_kombu_sdk-0.1.0.dist-info/METADATA
wdg_kombu_sdk-0.1.0.dist-info/WHEEL
wdg_kombu_sdk-0.1.0.dist-info/top_level.txt
wdg_kombu_sdk-0.1.0.dist-info/RECORD
