Metadata-Version: 2.1
Name: wdg-kombu-sdk
Version: 0.1.0
Summary: Reusable Kombu-based publisher/consumer SDK for Django projects.
Home-page: https://github.com/yourusername/wdg-kombu-sdk
Author: Your Name
Author-email: your.email@example.com
License: UNKNOWN
Platform: UNKNOWN
Classifier: Programming Language :: Python :: 3
Classifier: Framework :: Django
Classifier: License :: OSI Approved :: MIT License
Classifier: Operating System :: OS Independent
Requires-Python: >=3.7
Requires-Dist: kombu>=5.0.0
Requires-Dist: Django>=3.2
